lishoginet.py
lishoginet-2.0.0.dist-info/LICENSE.txt
lishoginet-2.0.0.dist-info/METADATA
lishoginet-2.0.0.dist-info/WHEEL
lishoginet-2.0.0.dist-info/top_level.txt
lishoginet-2.0.0.dist-info/RECORD
