Metadata-Version: 2.1
Name: lishoginet
Version: 2.0.0
Summary: Distributed Fairy-Stockfish analysis for lishogi.org
Home-page: https://github.com/TheYoBots/lishoginet
Author: Yohaan Nathan
Author-email: yohaan.nathanjw@gmail.com
License: UNKNOWN
Keywords: lishogi.org lishogi shogi stockfish usi
Platform: UNKNOWN
Classifier: Development Status :: 5 - Production/Stable
Classifier: Environment :: Console
Classifier: Intended Audience :: Developers
Classifier: Intended Audience :: End Users/Desktop
Classifier: License :: OSI Approved :: GNU General Public License v3 or later (GPLv3+)
Classifier: Operating System :: OS Independent
Classifier: Programming Language :: Python
Classifier: Programming Language :: Python :: 3
Classifier: Programming Language :: Python :: 3.7
Classifier: Programming Language :: Python :: 3.8
Classifier: Programming Language :: Python :: 3.9
Classifier: Programming Language :: Python :: 3.10
Classifier: Topic :: Games/Entertainment :: Board Games
Classifier: Topic :: Internet :: WWW/HTTP
Requires-Python: >=3.7
License-File: LICENSE.txt
Requires-Dist: requests (<3,>=2)
